extras/__init__.py
rahavard-1.0.0.dist-info/METADATA
rahavard-1.0.0.dist-info/WHEEL
rahavard-1.0.0.dist-info/top_level.txt
rahavard-1.0.0.dist-info/RECORD
