Metadata-Version: 2.1
Name: rahavard
Version: 1.0.0
Summary: Re-Usable Utils
Author: Davoud Arsalani
Author-email: d_arsalani@yahoo.com
Keywords: python
Classifier: Development Status :: 3 - Alpha
Classifier: Intended Audience :: Education
Classifier: Programming Language :: Python :: 2
Classifier: Programming Language :: Python :: 3
Classifier: Operating System :: MacOS :: MacOS X
Classifier: Operating System :: Microsoft :: Windows
